neer/__init__.py
neer/base.py
neer/predictions/__init__.py
neer/predictions/predictions/__init__.py
neer/predictions/predictions/event_analysis_results.py
neer/predictions/predictions/spark_report_link_bre.py
neer/predictions/predictions/spark_report_link_cof.py
neer/predictions/predictions/spark_report_link_lof.py
neer/predictions/predictions/spark_report_links.py
neer/predictions/predictions/spark_report_links_1d.py
neer/predictions/predictions/spark_report_links_1h.py
neer/predictions/predictions/spark_report_links_30d.py
neer/predictions/predictions/spark_report_links_5m.py
neer/predictions/predictions/spark_report_links_dw.py
neer/predictions/predictions/spark_report_links_dw_1d.py
neer/predictions/predictions/spark_report_links_dw_1h.py
neer/predictions/predictions/spark_report_links_dw_30d.py
neer/predictions/predictions/spark_report_links_dw_5m.py
neer/predictions/predictions/spark_report_node_bre.py
neer/predictions/predictions/spark_report_node_cof.py
neer/predictions/predictions/spark_report_node_lof.py
neer/predictions/predictions/spark_report_nodes.py
neer/predictions/predictions/spark_report_nodes_1d.py
neer/predictions/predictions/spark_report_nodes_1h.py
neer/predictions/predictions/spark_report_nodes_30d.py
neer/predictions/predictions/spark_report_nodes_5m.py
neer/predictions/predictions/spark_report_nodes_dw.py
neer/predictions/predictions/spark_report_nodes_dw_1d.py
neer/predictions/predictions/spark_report_nodes_dw_1h.py
neer/predictions/predictions/spark_report_nodes_dw_30d.py
neer/predictions/predictions/spark_report_nodes_dw_5m.py
neer/predictions/predictions/spark_report_subcatchments.py
neer/predictions/predictions/spark_report_subcatchments_1d.py
neer/predictions/predictions/spark_report_subcatchments_1h.py
neer/predictions/predictions/spark_report_subcatchments_30d.py
neer/predictions/predictions/spark_report_subcatchments_5m.py
neer/predictions/predictions/spark_rpt_conduit_surcharge_summaries.py
neer-0.0.8.dist-info/METADATA
neer-0.0.8.dist-info/WHEEL
neer-0.0.8.dist-info/top_level.txt
neer-0.0.8.dist-info/RECORD
