Metadata-Version: 2.1
Name: neer
Version: 0.0.8
Project-URL: Homepage, https://github.com/neerinc/pyoneer
Project-URL: Bug Tracker, https://github.com/neerinc/pyoneer/issues
Classifier: Programming Language :: Python :: 3
Classifier: Operating System :: OS Independent
Requires-Python: >=3.7
Requires-Dist: sqlalchemy (>=1.4.23)
Requires-Dist: loguru (>=0.5.3)
Requires-Dist: python-dotenv (>=0.21.1)
